pl_utils/__init__.py
pl_utils/_nbdev.py
pl_utils/imagenette_datamodule.py
pl_utils/imagenette_datamodule_fast.py
pl_utils/utils.py
pl_utils-0.0.1.dist-info/LICENSE
pl_utils-0.0.1.dist-info/METADATA
pl_utils-0.0.1.dist-info/WHEEL
pl_utils-0.0.1.dist-info/entry_points.txt
pl_utils-0.0.1.dist-info/top_level.txt
pl_utils-0.0.1.dist-info/RECORD
