Metadata-Version: 2.1
Name: pl-utils
Version: 0.0.1
Summary: utils for pytorch lightning
Home-page: https://github.com/ayasyrev/pl_utils/tree/master/
Author: Andrei Yasyrev
Author-email: a.yasyrev@gmail.com
License: Apache Software License 2.0
Keywords: utils pytorch lightning
Platform: UNKNOWN
Classifier: Development Status :: 3 - Alpha
Classifier: Intended Audience :: Developers
Classifier: License :: OSI Approved :: Apache Software License
Classifier: Natural Language :: English
Classifier: Programming Language :: Python :: 3.6
Classifier: Programming Language :: Python :: 3.7
Classifier: Programming Language :: Python :: 3.8
Requires-Python: >=3.6
Requires-Dist: pytorch-lightning
